coopmongo/__init__.py
coopmongo/constants.py
coopmongo/errors.py
coopmongo/facades.py
coopmongo/mongoCollectionDataStore.py
coopmongo/mongoCollectionHandler.py
coopmongo/mongoCommandStore.py
coopmongo/mongo_utils.py
coopmongo-0.4.dist-info/METADATA
coopmongo-0.4.dist-info/WHEEL
coopmongo-0.4.dist-info/top_level.txt
coopmongo-0.4.dist-info/RECORD
