Metadata-Version: 2.1
Name: coopmongo
Version: 0.4
Summary: Basic interaction with a mongodb
Home-page: https://github.com/tylertjburns/coopmongo
Author: tburns
Author-email: tyler.tj.burns@gmail.com
License: MIT
Classifier: Development Status :: 3 - Alpha
Classifier: License :: OSI Approved :: MIT License
Classifier: Programming Language :: Python
Classifier: Programming Language :: Python :: 3.5
Classifier: Programming Language :: Python :: 3.6
Classifier: Topic :: Software Development :: Libraries
Classifier: Topic :: Software Development :: Libraries :: Python Modules
Classifier: Intended Audience :: Developers
Requires-Python: >3.10
Requires-Dist: annotated-types ==0.7.0
Requires-Dist: anyio ==3.6.2
Requires-Dist: certifi ==2024.7.4
Requires-Dist: charset-normalizer ==3.3.2
Requires-Dist: cooptools ==1.32
Requires-Dist: dnspython ==2.2.1
Requires-Dist: docutils ==0.21.2
Requires-Dist: fastapi ==0.88.0
Requires-Dist: fonttools ==4.42.0
Requires-Dist: idna ==3.4
Requires-Dist: importlib-metadata ==8.2.0
Requires-Dist: jaraco.classes ==3.4.0
Requires-Dist: jaraco.context ==5.3.0
Requires-Dist: jaraco.functools ==4.0.2
Requires-Dist: keyring ==25.3.0
Requires-Dist: markdown-it-py ==3.0.0
Requires-Dist: mdurl ==0.1.2
Requires-Dist: more-itertools ==10.4.0
Requires-Dist: nh3 ==0.2.18
Requires-Dist: numpy ==2.0.1
Requires-Dist: packaging ==23.1
Requires-Dist: pandas ==2.2.2
Requires-Dist: pkginfo ==1.10.0
Requires-Dist: pydantic ==1.10.2
Requires-Dist: pydantic-core ==2.20.1
Requires-Dist: Pygments ==2.18.0
Requires-Dist: pymongo ==4.3.3
Requires-Dist: python-dateutil ==2.9.0.post0
Requires-Dist: pytz ==2024.1
Requires-Dist: pywin32-ctypes ==0.2.2
Requires-Dist: readme-renderer ==44.0
Requires-Dist: requests ==2.32.3
Requires-Dist: requests-toolbelt ==1.0.0
Requires-Dist: rfc3986 ==2.0.0
Requires-Dist: rich ==13.7.1
Requires-Dist: setuptools ==72.1.0
Requires-Dist: six ==1.16.0
Requires-Dist: sniffio ==1.3.0
Requires-Dist: starlette ==0.22.0
Requires-Dist: twine ==5.1.1
Requires-Dist: typing-extensions ==4.12.2
Requires-Dist: tzdata ==2024.1
Requires-Dist: urllib3 ==2.2.2
Requires-Dist: zipp ==3.19.2
